Workbook

Sheet Contabilidad
A1: Análisis Financiero por Cultivo — Contabilidad Financiera
A2: Celdas en AZUL = datos del SIAP (no modificar) | Celdas en AMARILLO = llenar con precios investigados
A3: Cultivo | B3: Rendimiento (ton/ha) | C3: Precio/ton ()* | D3: Ingreso Bruto ($/ha) | E3: Costo Prod. ($/ha)* | F3: Margen Bruto ($/ha) | G3: Pto. Equilibrio (ton) | H3: Viable
A4: Maíz grano | B4: 3.52 | C4: 4800 | D4: =B4*C4 | E4: 15000 | F4: =D4-E4 | G4: =IFERROR(E4/C4,0) | H4: =IF(F4>0,"✓ Sí","✗ No")
A5: Tomate rojo (jitomate) | B5: 68.68 | C5: 8000 | D5: =B5*C5 | E5: 120000 | F5: =D5-E5 | G5: =IFERROR(E5/C5,0) | H5: =IF(F5>0,"✓ Sí","✗ No")
A6: Aguacate | B6: 10.65 | C6: 25000 | D6: =B6*C6 | E6: 45000 | F6: =D6-E6 | G6: =IFERROR(E6/C6,0) | H6: =IF(F6>0,"✓ Sí","✗ No")
A7: Chile verde | B7: 20.15 | C7: 6000 | D7: =B7*C7 | E7: 35000 | F7: =D7-E7 | G7: =IFERROR(E7/C7,0) | H7: =IF(F7>0,"✓ Sí","✗ No")
A8: Frijol | B8: 0.89 | C8: 9000 | D8: =B8*C8 | E8: 18000 | F8: =D8-E8 | G8: =IFERROR(E8/C8,0) | H8: =IF(F8>0,"✓ Sí","✗ No")
A9: Papa | B9: 32.33 | C9: 4500 | D9: =B9*C9 | E9: 40000 | F9: =D9-E9 | G9: =IFERROR(E9/C9,0) | H9: =IF(F9>0,"✓ Sí","✗ No")
A10: Cebolla | B10: 30.89 | C10: 3500 | D10: =B10*C10 | E10: 25000 | F10: =D10-E10 | G10: =IFERROR(E10/C10,0) | H10: =IF(F10>0,"✓ Sí","✗ No")
A11: Espárrago | B11: 8.66 | C11: 30000 | D11: =B11*C11 | E11: 60000 | F11: =D11-E11 | G11: =IFERROR(E11/C11,0) | H11: =IF(F11>0,"✓ Sí","✗ No")
A12: Brócoli | B12: 17.37 | C12: 5000 | D12: =B12*C12 | E12: 30000 | F12: =D12-E12 | G12: =IFERROR(E12/C12,0) | H12: =IF(F12>0,"✓ Sí","✗ No")
A13: Naranja | B13: 13.46 | C13: 3000 | D13: =B13*C13 | E13: 20000 | F13: =D13-E13 | G13: =IFERROR(E13/C13,0) | H13: =IF(F13>0,"✓ Sí","✗ No")
A15: * Precios referencia: SADER precios medios rurales 2025 | Costos referencia: FIRA costos de producción 2025

Sheet Probabilidad
A1: Análisis de Riesgo por Cultivo — Probabilidad
A2: P(pérdida) se calcula desde tasa de siniestro del SIAP | Ingreso bruto viene de hoja Contabilidad
A3: Cultivo | B3: Tasa Siniestro (%) | C3: P(pérdida) | D3: P(éxito) | E3: Ingreso Bruto ($/ha) | F3: Valor Esperado Utilidad ($/ha) | G3: Clasificación Riesgo
A4: Maíz grano | B4: 0.012573 | C4: =B4 | D4: =1-C4 | E4: 16896 | F4: =D4*E4-15000 | G4: =IF(AND(C4<0.02,E4>50000),"Alto rend. / Bajo riesgo",IF(AND(C4<0.02,E4<=50000),"Bajo rend. / Bajo riesgo",IF(AND(C4>=0.02,E4>50000),"Alto rend. / Alto riesgo","Bajo rend. / Alto riesgo")))
A5: Tomate rojo (jitomate) | B5: 0.006537 | C5: =B5 | D5: =1-C5 | E5: 549440 | F5: =D5*E5-120000 | G5: =IF(AND(C5<0.02,E5>50000),"Alto rend. / Bajo riesgo",IF(AND(C5<0.02,E5<=50000),"Bajo rend. / Bajo riesgo",IF(AND(C5>=0.02,E5>50000),"Alto rend. / Alto riesgo","Bajo rend. / Alto riesgo")))
A6: Aguacate | B6: 3.7e-05 | C6: =B6 | D6: =1-C6 | E6: 266250 | F6: =D6*E6-45000 | G6: =IF(AND(C6<0.02,E6>50000),"Alto rend. / Bajo riesgo",IF(AND(C6<0.02,E6<=50000),"Bajo rend. / Bajo riesgo",IF(AND(C6>=0.02,E6>50000),"Alto rend. / Alto riesgo","Bajo rend. / Alto riesgo")))
A7: Chile verde | B7: 0.002798 | C7: =B7 | D7: =1-C7 | E7: 120900 | F7: =D7*E7-35000 | G7: =IF(AND(C7<0.02,E7>50000),"Alto rend. / Bajo riesgo",IF(AND(C7<0.02,E7<=50000),"Bajo rend. / Bajo riesgo",IF(AND(C7>=0.02,E7>50000),"Alto rend. / Alto riesgo","Bajo rend. / Alto riesgo")))
A8: Frijol | B8: 0.009728 | C8: =B8 | D8: =1-C8 | E8: 8010 | F8: =D8*E8-18000 | G8: =IF(AND(C8<0.02,E8>50000),"Alto rend. / Bajo riesgo",IF(AND(C8<0.02,E8<=50000),"Bajo rend. / Bajo riesgo",IF(AND(C8>=0.02,E8>50000),"Alto rend. / Alto riesgo","Bajo rend. / Alto riesgo")))
A9: Papa | B9: 0.000799 | C9: =B9 | D9: =1-C9 | E9: 145485 | F9: =D9*E9-40000 | G9: =IF(AND(C9<0.02,E9>50000),"Alto rend. / Bajo riesgo",IF(AND(C9<0.02,E9<=50000),"Bajo rend. / Bajo riesgo",IF(AND(C9>=0.02,E9>50000),"Alto rend. / Alto riesgo","Bajo rend. / Alto riesgo")))
A10: Cebolla | B10: 0.004759 | C10: =B10 | D10: =1-C10 | E10: 108115 | F10: =D10*E10-25000 | G10: =IF(AND(C10<0.02,E10>50000),"Alto rend. / Bajo riesgo",IF(AND(C10<0.02,E10<=50000),"Bajo rend. / Bajo riesgo",IF(AND(C10>=0.02,E10>50000),"Alto rend. / Alto riesgo","Bajo rend. / Alto riesgo")))
A11: Espárrago | B11: 0.000326 | C11: =B11 | D11: =1-C11 | E11: 259800 | F11: =D11*E11-60000 | G11: =IF(AND(C11<0.02,E11>50000),"Alto rend. / Bajo riesgo",IF(AND(C11<0.02,E11<=50000),"Bajo rend. / Bajo riesgo",IF(AND(C11>=0.02,E11>50000),"Alto rend. / Alto riesgo","Bajo rend. / Alto riesgo")))
A12: Brócoli | B12: 0.010185 | C12: =B12 | D12: =1-C12 | E12: 86850 | F12: =D12*E12-30000 | G12: =IF(AND(C12<0.02,E12>50000),"Alto rend. / Bajo riesgo",IF(AND(C12<0.02,E12<=50000),"Bajo rend. / Bajo riesgo",IF(AND(C12>=0.02,E12>50000),"Alto rend. / Alto riesgo","Bajo rend. / Alto riesgo")))
A13: Naranja | B13: 0.000151 | C13: =B13 | D13: =1-C13 | E13: 40380 | F13: =D13*E13-20000 | G13: =IF(AND(C13<0.02,E13>50000),"Alto rend. / Bajo riesgo",IF(AND(C13<0.02,E13<=50000),"Bajo rend. / Bajo riesgo",IF(AND(C13>=0.02,E13>50000),"Alto rend. / Alto riesgo","Bajo rend. / Alto riesgo")))

Sheet Calculo Integral
A1: Modelo de Producción Acumulada — Cálculo Integral
A2: Modelo: f(t) = a·t donde a = producción_total/12 | Integral definida de 0 a 12 meses
A3: Cultivo | B3: Producción Total (ton) | C3: a = Prod/12 (ton/mes) | D3: Integral ∫₀¹² a·t dt | E3: Costo Marginal ($/ha)* | F3: Costo Total ∫ Cmg dx | G3: Excedente Productor
A4: Maíz grano | B4: 18998771 | C4: =B4/12 | D4: =C4*72 | E4: 15000 | F4: =E4*1 | G4: =D4*0.0048-F4
A5: Tomate rojo (jitomate) | B5: 2807090 | C5: =B5/12 | D5: =C5*72 | E5: 120000 | F5: =E5*1 | G5: =D5*0.0080-F5
A6: Aguacate | B6: 2725079.6 | C6: =B6/12 | D6: =C6*72 | E6: 45000 | F6: =E6*1 | G6: =D6*0.0250-F6
A7: Chile verde | B7: 2847967.8 | C7: =B7/12 | D7: =C7*72 | E7: 35000 | F7: =E7*1 | G7: =D7*0.0060-F7
A8: Frijol | B8: 1121513.8 | C8: =B8/12 | D8: =C8*72 | E8: 18000 | F8: =E8*1 | G8: =D8*0.0090-F8
A9: Papa | B9: 2161843.6 | C9: =B9/12 | D9: =C9*72 | E9: 40000 | F9: =E9*1 | G9: =D9*0.0045-F9
A10: Cebolla | B10: 1368238.7 | C10: =B10/12 | D10: =C10*72 | E10: 25000 | F10: =E10*1 | G10: =D10*0.0035-F10
A11: Espárrago | B11: 287592.75 | C11: =B11/12 | D11: =C11*72 | E11: 60000 | F11: =E11*1 | G11: =D11*0.0300-F11
A12: Brócoli | B12: 551627.88 | C12: =B12/12 | D12: =C12*72 | E12: 30000 | F12: =E12*1 | G12: =D12*0.0050-F12
A13: Naranja | B13: 4627370.1 | C13: =B13/12 | D13: =C13*72 | E13: 20000 | F13: =E13*1 | G13: =D13*0.0030-F13
A15: * Modelo simplificado f(t)=a·t para ciclo de 12 meses | ∫₀¹² a·t dt = a·(12²/2) = 72a | Verificar con GeoGebra

Sheet Resumen Integrado
A1: Resumen Integrado — Recomendación de Cultivos
A3: Cultivo | B3: Margen Bruto (Contabilidad) | C3: Valor Esperado (Probabilidad) | D3: Prod. Acumulada (Cálculo) | E3: Score General | F3: Recomendación
A4: Maíz grano | B4: =Contabilidad!F4 | C4: =Probabilidad!F4 | D4: ="Calculo Integral"!D4 | E4: =RANK(B4,B4:B13,0) | F4: =IF(E4<=3,"Alta prioridad",IF(E4<=6,"Media prioridad","Baja prioridad"))
A5: Tomate rojo (jitomate) | B5: =Contabilidad!F5 | C5: =Probabilidad!F5 | D5: ="Calculo Integral"!D5 | E5: =RANK(B5,B4:B13,0) | F5: =IF(E5<=3,"Alta prioridad",IF(E5<=6,"Media prioridad","Baja prioridad"))
A6: Aguacate | B6: =Contabilidad!F6 | C6: =Probabilidad!F6 | D6: ="Calculo Integral"!D6 | E6: =RANK(B6,B4:B13,0) | F6: =IF(E6<=3,"Alta prioridad",IF(E6<=6,"Media prioridad","Baja prioridad"))
A7: Chile verde | B7: =Contabilidad!F7 | C7: =Probabilidad!F7 | D7: ="Calculo Integral"!D7 | E7: =RANK(B7,B4:B13,0) | F7: =IF(E7<=3,"Alta prioridad",IF(E7<=6,"Media prioridad","Baja prioridad"))
A8: Frijol | B8: =Contabilidad!F8 | C8: =Probabilidad!F8 | D8: ="Calculo Integral"!D8 | E8: =RANK(B8,B4:B13,0) | F8: =IF(E8<=3,"Alta prioridad",IF(E8<=6,"Media prioridad","Baja prioridad"))
A9: Papa | B9: =Contabilidad!F9 | C9: =Probabilidad!F9 | D9: ="Calculo Integral"!D9 | E9: =RANK(B9,B4:B13,0) | F9: =IF(E9<=3,"Alta prioridad",IF(E9<=6,"Media prioridad","Baja prioridad"))
A10: Cebolla | B10: =Contabilidad!F10 | C10: =Probabilidad!F10 | D10: ="Calculo Integral"!D10 | E10: =RANK(B10,B4:B13,0) | F10: =IF(E10<=3,"Alta prioridad",IF(E10<=6,"Media prioridad","Baja prioridad"))
A11: Espárrago | B11: =Contabilidad!F11 | C11: =Probabilidad!F11 | D11: ="Calculo Integral"!D11 | E11: =RANK(B11,B4:B13,0) | F11: =IF(E11<=3,"Alta prioridad",IF(E11<=6,"Media prioridad","Baja prioridad"))
A12: Brócoli | B12: =Contabilidad!F12 | C12: =Probabilidad!F12 | D12: ="Calculo Integral"!D12 | E12: =RANK(B12,B4:B13,0) | F12: =IF(E12<=3,"Alta prioridad",IF(E12<=6,"Media prioridad","Baja prioridad"))
A13: Naranja | B13: =Contabilidad!F13 | C13: =Probabilidad!F13 | D13: ="Calculo Integral"!D13 | E13: =RANK(B13,B4:B13,0) | F13: =IF(E13<=3,"Alta prioridad",IF(E13<=6,"Media prioridad","Baja prioridad"))
